pylocksfile.py
tests/__init__.py
tests/tests.py
pylocksfile-0.0.6.dist-info/METADATA
pylocksfile-0.0.6.dist-info/WHEEL
pylocksfile-0.0.6.dist-info/top_level.txt
pylocksfile-0.0.6.dist-info/RECORD
