Metadata-Version: 2.1
Name: pylocksfile
Version: 0.0.6
Summary: Python library for linux file-based read/write locks for inter-process communication
Home-page: https://github.com/Meidar-S/pylocksfile
Author: Meidar Sharkansky
Author-email: meidarsharkansky@gmail.com
License: UNKNOWN
Platform: UNKNOWN
Classifier: Programming Language :: Python :: 3
Classifier: License :: OSI Approved :: MIT License
Classifier: Operating System :: OS Independent
Requires-Python: >=3.6
